AUTHORS.rst
CONTRIBUTING.rst
HISTORY.rst
LICENSE
MANIFEST.in
README.rst
setup.cfg
setup.py
docs/Makefile
docs/authors.rst
docs/conf.py
docs/contributing.rst
docs/history.rst
docs/index.rst
docs/installation.rst
docs/make.bat
docs/readme.rst
docs/usage.rst
tests/test_treeio.py
treeio/__init__.py
treeio/cli.py
treeio/treeio.py
treeio.egg-info/PKG-INFO
treeio.egg-info/SOURCES.txt
treeio.egg-info/dependency_links.txt
treeio.egg-info/entry_points.txt
treeio.egg-info/not-zip-safe
treeio.egg-info/requires.txt
treeio.egg-info/top_level.txt