Metadata-Version: 1.1
Name: treeio
Version: 0.0.0.dev0
Summary: A pure python parser for tree data format IO
Home-page: https://github.com/yech1990/treeio
Author: Ye Chang
Author-email: yech1990@gmail.com
License: MIT license
Keywords: treeio
Platform: UNKNOWN
Classifier: Development Status :: 2 - Pre-Alpha
Classifier: Intended Audience :: Developers
Classifier: License :: OSI Approved :: MIT License
Classifier: Natural Language :: English
Classifier: Programming Language :: Python :: 2
Classifier: Programming Language :: Python :: 2.7
Classifier: Programming Language :: Python :: 3
Classifier: Programming Language :: Python :: 3.4
Classifier: Programming Language :: Python :: 3.5
Classifier: Programming Language :: Python :: 3.6
Classifier: Programming Language :: Python :: 3.7
